tbusd_escrow/__init__.py
tbusd_escrow/escrow.py
tbusd_escrow-0.1.0.dist-info/METADATA
tbusd_escrow-0.1.0.dist-info/WHEEL
tbusd_escrow-0.1.0.dist-info/RECORD
