Metadata-Version: 2.4
Name: tbusd-escrow
Version: 0.1.0
Summary: Trustless escrow API for crypto payments - programmatic smart contract escrow on Base
Project-URL: Homepage, https://tbusd.io/escrow/
Project-URL: Documentation, https://tbusd.io/escrow/developers
Project-URL: Repository, https://github.com/tbusd/escrow-python-sdk
Author-email: TBUSD <dev@tbusd.io>
License: MIT
Keywords: ai-agent,autonomous,base,crypto,escrow,escrow-api,ethereum,payment-api,payments,programmatic,smart-contracts,stablecoin,tbusd,trustless,web3
Classifier: Development Status :: 4 - Beta
Classifier: Intended Audience :: Developers
Classifier: License :: OSI Approved :: MIT License
Classifier: Programming Language :: Python :: 3
Classifier: Programming Language :: Python :: 3.8
Classifier: Programming Language :: Python :: 3.9
Classifier: Programming Language :: Python :: 3.10
Classifier: Programming Language :: Python :: 3.11
Classifier: Programming Language :: Python :: 3.12
Classifier: Topic :: Office/Business :: Financial
Classifier: Topic :: Software Development :: Libraries :: Python Modules
Requires-Python: >=3.8
Requires-Dist: eth-account>=0.8.0
Requires-Dist: web3>=6.0.0
